xbackend/__init__.py
xbackend-0.1.0.dist-info/LICENSE
xbackend-0.1.0.dist-info/METADATA
xbackend-0.1.0.dist-info/WHEEL
xbackend-0.1.0.dist-info/RECORD
