Metadata-Version: 2.1
Name: xbackend
Version: 0.1.0
Summary: 
Author: mathewgeola
Author-email: mathewgeola@163.com
Requires-Python: >=3.10,<4.0
Classifier: Programming Language :: Python :: 3
Classifier: Programming Language :: Python :: 3.10
Classifier: Programming Language :: Python :: 3.11
Classifier: Programming Language :: Python :: 3.12
Requires-Dist: django (==5.0.0)
Requires-Dist: djangorestframework (>=3.15.2,<4.0.0)
